{
    "config": {
        "ratio": 0.8,
        "priority": 5
    },
    "variables": {
        "Visual Studio Code - Dark": {
            "home.recent.topButtons.iconColor": "#FFFFFF",
            "project.toolbar.iconColor": "#FFFFFF",
            "project.floatingPanel.iconColor": "#FFFFFF",
            "project.dockCard.iconColor": "#CCCCCC",
            "project.dockCard.iconColor.checked": "#FFFFFF",
            "project.sidePanel.iconColor": "#CCCCCC",
            "project.sidePanel.iconColor.checked": "#FFFFFF"
        },
        "Visual Studio Code - Light": {
            "home.recent.topButtons.iconColor": "#FFFFFF",
            "project.toolbar.iconColor": "#FFFFFF",
            "project.floatingPanel.iconColor": "#FFFFFF",
            "project.sidePanel.iconColor": "#CCCCCC",
            "project.sidePanel.iconColor.checked": "#FFFFFF"
        }
    },
    "stylesheets": {
        "_common": {
            "Global": [
                {
                    "content": {
                        "win": "/* QWidget { font-size: \"Microsoft YaHei\"; } */",
                        "linux": "QWidget[top-window=true] { qproperty-windowIcon: url(\":/svg/app/diffsinger\"); }"
                    }
                }
            ]
        },
        "Visual Studio Code - Dark": {
            "Global": {
                "file": "global-dark.qss"
            },
            "Core::HomeWindow": {
                "file": "home-dark.qss"
            },
            "Core::ProjectWindow": {
                "file": "project-dark.qss"
            },
            "Core::IDockPanel": {
                "file": "side-panel-dark.qss"
            }
        },
        "Visual Studio Code - Light": {
            "Global": {
                "file": "global-light.qss"
            },
            "Core::HomeWindow": {
                "file": "home-light.qss"
            },
            "Core::ProjectWindow": {
                "file": "project-light.qss"
            },
            "Core::IDockPanel": {
                "file": "side-panel-light.qss"
            }
        }
    },
    "widgets": {
        "core.HomeWindow": [
            "Global",
            "Core::HomeWindow"
        ],
        "core.ProjectWindow": [
            "Global",
            "Core::ProjectWindow"
        ],
        "core.IDockPanel": [
            "Global",
            "Core::IDockPanel"
        ]
    }
}